AUTHORS
CHANGELOG.txt
DESCRIPTION
LICENSE
MANIFEST.in
README.rst
requirements.txt
setup.cfg
setup.py
tox.ini
django_server_guardian_api.egg-info/PKG-INFO
django_server_guardian_api.egg-info/SOURCES.txt
django_server_guardian_api.egg-info/dependency_links.txt
django_server_guardian_api.egg-info/requires.txt
django_server_guardian_api.egg-info/top_level.txt
server_guardian_api/__init__.py
server_guardian_api/constants.py
server_guardian_api/default_settings.py
server_guardian_api/urls.py
server_guardian_api/views.py
server_guardian_api/processors/__init__.py
server_guardian_api/processors/debug.py
server_guardian_api/processors/django_mailer.py
server_guardian_api/tests/__init__.py
server_guardian_api/tests/processors_tests.py
server_guardian_api/tests/settings.py
server_guardian_api/tests/test_settings.py
server_guardian_api/tests/urls.py
server_guardian_api/tests/views_tests.py