Metadata-Version: 1.0
Name: django-server-guardian-api
Version: 0.1.2
Summary: API offering health metrics for the ``django-server-guardian`` app.
